ltsvlogger.py
ltsvlogger-0.9.1.dist-info/DESCRIPTION.rst
ltsvlogger-0.9.1.dist-info/METADATA
ltsvlogger-0.9.1.dist-info/RECORD
ltsvlogger-0.9.1.dist-info/WHEEL
ltsvlogger-0.9.1.dist-info/metadata.json
ltsvlogger-0.9.1.dist-info/namespace_packages.txt
ltsvlogger-0.9.1.dist-info/top_level.txt
