Metadata-Version: 2.0
Name: ltsvlogger
Version: 0.9.1
Summary: labeled TSV logger.
Home-page: https://bitbucket.org/shimizukawa/ltsvlogger
Author: Takayuki SHIMIZUKAWA
Author-email: shimizukawa@gmail.com
License: UNKNOWN
Platform: UNKNOWN
Classifier: Development Status :: 4 - Beta
Classifier: Environment :: Other Environment
Classifier: License :: OSI Approved :: Apache Software License
Classifier: Topic :: System :: Logging
Classifier: Topic :: Utilities
Classifier: Programming Language :: Python
Classifier: Programming Language :: Python :: 2
Classifier: Programming Language :: Python :: 2.6
Classifier: Programming Language :: Python :: 2.7
Classifier: Programming Language :: Python :: 3
Classifier: Programming Language :: Python :: 3.2
Classifier: Programming Language :: Python :: 3.3
Classifier: Programming Language :: Python :: 3.4
Classifier: Programming Language :: Python :: 3.5
